odoo/addons/server_env_printing_server/README.rst
odoo/addons/server_env_printing_server/__init__.py
odoo/addons/server_env_printing_server/__manifest__.py
odoo/addons/server_env_printing_server/i18n/it.po
odoo/addons/server_env_printing_server/i18n/server_env_printing_server.pot
odoo/addons/server_env_printing_server/models/__init__.py
odoo/addons/server_env_printing_server/models/printing_server.py
odoo/addons/server_env_printing_server/readme/CONTRIBUTORS.rst
odoo/addons/server_env_printing_server/readme/CREDITS.rst
odoo/addons/server_env_printing_server/readme/DESCRIPTION.rst
odoo/addons/server_env_printing_server/static/description/icon.png
odoo/addons/server_env_printing_server/static/description/index.html
odoo14_addon_server_env_printing_server-14.0.1.0.1.dist-info/METADATA
odoo14_addon_server_env_printing_server-14.0.1.0.1.dist-info/WHEEL
odoo14_addon_server_env_printing_server-14.0.1.0.1.dist-info/top_level.txt
odoo14_addon_server_env_printing_server-14.0.1.0.1.dist-info/RECORD
