Metadata-Version: 2.1
Name: odoo14-addon-server_env_printing_server
Version: 14.0.1.0.1
Summary: Server Environment for Printing Server
Home-page: https://github.com/OCA/report-print-send
Author: Camptocamp, Odoo Community Association (OCA)
Author-email: support@odoo-community.org
License: AGPL-3
Classifier: Programming Language :: Python
Classifier: Framework :: Odoo
Classifier: Framework :: Odoo :: 14.0
Classifier: License :: OSI Approved :: GNU Affero General Public License v3
Requires-Python: >=3.6
Requires-Dist: odoo14-addon-base-report-to-printer
Requires-Dist: odoo14-addon-server-environment
Requires-Dist: odoo <14.1dev,>=14.0a
